py.typed
emissary_client_sdk/__init__.py
emissary_client_sdk/_hooks/__init__.py
emissary_client_sdk/_hooks/registration.py
emissary_client_sdk/_hooks/sdkhooks.py
emissary_client_sdk/_hooks/types.py
emissary_client_sdk/_version.py
emissary_client_sdk/basemodels.py
emissary_client_sdk/basesdk.py
emissary_client_sdk/chat.py
emissary_client_sdk/classification.py
emissary_client_sdk/completions.py
emissary_client_sdk/datasets.py
emissary_client_sdk/deployments.py
emissary_client_sdk/embeddings.py
emissary_client_sdk/emissaryclient_completions.py
emissary_client_sdk/httpclient.py
emissary_client_sdk/models/__init__.py
emissary_client_sdk/models/apierrorinvalidinput.py
emissary_client_sdk/models/apierrornotfound.py
emissary_client_sdk/models/apierrorunauthorized.py
emissary_client_sdk/models/basemodelsummary.py
emissary_client_sdk/models/canceldeploymentbyidop.py
emissary_client_sdk/models/canceltrainingjobbyidop.py
emissary_client_sdk/models/createdatasetop.py
emissary_client_sdk/models/createdeploymentop.py
emissary_client_sdk/models/createprojectop.py
emissary_client_sdk/models/createtrainingjobop.py
emissary_client_sdk/models/datasetdetail.py
emissary_client_sdk/models/datasetsummary.py
emissary_client_sdk/models/deletedatasetbyidop.py
emissary_client_sdk/models/deletedeploymentbyidop.py
emissary_client_sdk/models/deleteprojectbyidop.py
emissary_client_sdk/models/deletetrainingjobbyidop.py
emissary_client_sdk/models/deploymentdetail.py
emissary_client_sdk/models/deploymentsummary.py
emissary_client_sdk/models/getchatcompletionsfromdeploymentop.py
emissary_client_sdk/models/getclassificationfromdeploymentop.py
emissary_client_sdk/models/getcompletionsfromdeploymentop.py
emissary_client_sdk/models/getembeddingsfromdeploymentop.py
emissary_client_sdk/models/listcheckpointsop.py
emissary_client_sdk/models/listdatasetsop.py
emissary_client_sdk/models/listdeploymentsop.py
emissary_client_sdk/models/listtrainingjobsop.py
emissary_client_sdk/models/projectdetail.py
emissary_client_sdk-0.4.4.dist-info/LICENSE
emissary_client_sdk-0.4.4.dist-info/METADATA
emissary_client_sdk-0.4.4.dist-info/WHEEL
emissary_client_sdk-0.4.4.dist-info/RECORD
