Metadata-Version: 2.1
Name: emissary-client-sdk
Version: 0.4.4
Summary: Python Client SDK for emissary.dev.
Home-page: https://github.com/Emissary-Tech/emissary-python.git
Author: Emissary
Requires-Python: >=3.8,<4.0
Classifier: Programming Language :: Python :: 3
Classifier: Programming Language :: Python :: 3.8
Classifier: Programming Language :: Python :: 3.9
Classifier: Programming Language :: Python :: 3.10
Classifier: Programming Language :: Python :: 3.11
Classifier: Programming Language :: Python :: 3.12
Classifier: Programming Language :: Python :: 3.13
Requires-Dist: eval-type-backport (>=0.2.0,<0.3.0)
Requires-Dist: httpx (>=0.27.0,<0.28.0)
Requires-Dist: jsonpath-python (>=1.0.6,<2.0.0)
Requires-Dist: pydantic (>=2.9.2,<2.10.0)
Requires-Dist: python-dateutil (==2.8.2)
Requires-Dist: typing-inspect (>=0.9.0,<0.10.0)
Project-URL: Repository, https://github.com/Emissary-Tech/emissary-python.git
